MANIFEST.in
README.md
setup.py
mmiisort/__init__.py
mmiisort/main.py
mothermayi_isort.egg-info/PKG-INFO
mothermayi_isort.egg-info/SOURCES.txt
mothermayi_isort.egg-info/dependency_links.txt
mothermayi_isort.egg-info/entry_points.txt
mothermayi_isort.egg-info/requires.txt
mothermayi_isort.egg-info/top_level.txt