Metadata-Version: 1.0
Name: mothermayi-isort
Version: 0.8
Summary: The isort plugin for mothermayi
Home-page: https://github.com/EliRibble/mothermayi-isort
Author: Eli Ribble
Author-email: junk@theribbles.org
License: UNKNOWN
Platform: UNKNOWN
